betwixt/__init__.py
betwixt/examples.py
betwixt-1.0.0.dist-info/AUTHORS.rst
betwixt-1.0.0.dist-info/LICENSE
betwixt-1.0.0.dist-info/METADATA
betwixt-1.0.0.dist-info/WHEEL
betwixt-1.0.0.dist-info/top_level.txt
betwixt-1.0.0.dist-info/zip-safe
betwixt-1.0.0.dist-info/RECORD
