Metadata-Version: 2.1
Name: betwixt
Version: 1.0.0
Summary: Infix operators for Python
Home-page: https://github.com/riccardomurri/betwixt
Author: Riccardo Murri
Author-email: riccardo.murri@gmail.com
License: GNU Lesser General Public License v3 or later (LGPLv3+)
Project-URL: Documentation, https://betwixt.readthedocs.io/
Project-URL: Changelog, https://betwixt.readthedocs.io/en/latest/changelog.html
Project-URL: Issue Tracker, https://github.com/riccardomurri/betwixt/issues
Platform: UNKNOWN
Classifier: Development Status :: 5 - Production/Stable
Classifier: Intended Audience :: Developers
Classifier: License :: OSI Approved :: GNU Lesser General Public License v3 or later (LGPLv3+)
Classifier: Operating System :: Unix
Classifier: Operating System :: POSIX
Classifier: Operating System :: Microsoft :: Windows
Classifier: Programming Language :: Python
Classifier: Programming Language :: Python :: 2
Classifier: Programming Language :: Python :: 2.7
Classifier: Programming Language :: Python :: 3
Classifier: Programming Language :: Python :: 3.4
Classifier: Programming Language :: Python :: 3.5
Classifier: Programming Language :: Python :: 3.6
Classifier: Programming Language :: Python :: 3.7
Classifier: Programming Language :: Python :: Implementation :: CPython
Classifier: Programming Language :: Python :: Implementation :: PyPy
Classifier: Topic :: Utilities
Requires-Python: >=2.7, !=3.0.*, !=3.1.*, !=3.2.*, !=3.3.*
